fibro/__init__.py
fibro/__main__.py
fibro/app.py
fibro/app.tcss
fibro/browser.py
fibro/config.py
fibro/directory.py
fibro/highlight.py
fibro/preview.py
fibro/prompt.py
fibro/simple_input.py
fibro/utils.py
fibro/helix/LICENSE
fibro/helix/base16_theme.toml
fibro/helix/theme.toml
fibro/helix/runtime/queries/_gjs/highlights.scm
fibro/helix/runtime/queries/_gjs/injections.scm
fibro/helix/runtime/queries/_javascript/highlights.scm
fibro/helix/runtime/queries/_javascript/locals.scm
fibro/helix/runtime/queries/_javascript/tags.scm
fibro/helix/runtime/queries/_jsx/highlights.scm
fibro/helix/runtime/queries/_jsx/indents.scm
fibro/helix/runtime/queries/_typescript/highlights.scm
fibro/helix/runtime/queries/_typescript/indents.scm
fibro/helix/runtime/queries/_typescript/locals.scm
fibro/helix/runtime/queries/_typescript/tags.scm
fibro/helix/runtime/queries/_typescript/textobjects.scm
fibro/helix/runtime/queries/ada/folds.scm
fibro/helix/runtime/queries/ada/highlights.scm
fibro/helix/runtime/queries/ada/locals.scm
fibro/helix/runtime/queries/ada/textobjects.scm
fibro/helix/runtime/queries/adl/highlights.scm
fibro/helix/runtime/queries/adl/indents.scm
fibro/helix/runtime/queries/adl/textobjects.scm
fibro/helix/runtime/queries/agda/highlights.scm
fibro/helix/runtime/queries/amber/highlights.scm
fibro/helix/runtime/queries/astro/highlights.scm
fibro/helix/runtime/queries/astro/injections.scm
fibro/helix/runtime/queries/awk/highlights.scm
fibro/helix/runtime/queries/awk/injections.scm
fibro/helix/runtime/queries/awk/textobjects.scm
fibro/helix/runtime/queries/bash/highlights.scm
fibro/helix/runtime/queries/bash/indents.scm
fibro/helix/runtime/queries/bash/injections.scm
fibro/helix/runtime/queries/bash/textobjects.scm
fibro/helix/runtime/queries/bass/highlights.scm
fibro/helix/runtime/queries/beancount/folds.scm
fibro/helix/runtime/queries/beancount/highlights.scm
fibro/helix/runtime/queries/bibtex/highlights.scm
fibro/helix/runtime/queries/bibtex/locals.scm
fibro-0.1.2.dist-info/METADATA
fibro-0.1.2.dist-info/WHEEL
fibro-0.1.2.dist-info/entry_points.txt
fibro-0.1.2.dist-info/RECORD
