Metadata-Version: 2.4
Name: fibro
Version: 0.1.2
Summary: A fuzzy search based filebrowser
Requires-Python: >=3.13
Requires-Dist: textual[syntax]>=1.0.0
